react_seqlogo/SequenceLogo.py
react_seqlogo/__init__.py
react_seqlogo/_imports_.py
react_seqlogo/async-SequenceLogo.js
react_seqlogo/async-SequenceLogo.js.map
react_seqlogo/metadata.json
react_seqlogo/package-info.json
react_seqlogo/react_seqlogo.min.js
react_seqlogo/react_seqlogo.min.js.map
react_seqlogo-0.0.1.dist-info/LICENSE
react_seqlogo-0.0.1.dist-info/METADATA
react_seqlogo-0.0.1.dist-info/WHEEL
react_seqlogo-0.0.1.dist-info/top_level.txt
react_seqlogo-0.0.1.dist-info/RECORD
